zops/__init__.py
zops/cf.py
zops/cli.py
zops/user.py
zops/util.py
zops/templates/flask.py.jinja2
zops/templates/zappa_settings.json.jinja2
zops/templates/templates/base.html
zops-0.2.5.dist-info/DESCRIPTION.rst
zops-0.2.5.dist-info/METADATA
zops-0.2.5.dist-info/RECORD
zops-0.2.5.dist-info/WHEEL
zops-0.2.5.dist-info/entry_points.txt
zops-0.2.5.dist-info/metadata.json
zops-0.2.5.dist-info/top_level.txt
