Metadata-Version: 2.0
Name: zops
Version: 0.2.5
Summary: Utils for devops teams that want to deploy using Zappa
Home-page: UNKNOWN
Author: Brian Jinwright
Author-email: opensource@ipoots.com
License: GNU GPL V3
Keywords: zappa,aws,lambda
Platform: UNKNOWN
Classifier: Programming Language :: Python
Classifier: Topic :: Software Development :: Libraries :: Python Modules
Classifier: Environment :: Web Environment
Requires-Dist: Flask (>=0.11.1)
Requires-Dist: Jinja2 (>=2.8)
Requires-Dist: Unipath (>=1.1)
Requires-Dist: awacs (>=0.6.0)
Requires-Dist: click (>=6.6)
Requires-Dist: terminaltables (>=3.0.0)
Requires-Dist: troposphere (>=1.8.0)
Requires-Dist: zappa (>=0.22.4)
